password_generator/__init__.py
password_generator/apps.py
password_generator/cli.py
password_generator/generator.py
password_generator/urls.py
password_generator/views.py
momopwdgen-1.0.0.dist-info/METADATA
momopwdgen-1.0.0.dist-info/WHEEL
momopwdgen-1.0.0.dist-info/entry_points.txt
momopwdgen-1.0.0.dist-info/top_level.txt
momopwdgen-1.0.0.dist-info/RECORD
